MANIFEST.in
setup.py
examples/2x16x16x16x3_multi_classification.py
examples/2x4x2.py
examples/2x8x8x2_neural_network.py
examples/2x8x8x8x8x2_grid_classification.py
examples/basic.py
examples/regression_neural_network.py
examples/solve_equation_set.py
examples/support_vector_machine.py
trik/__init__.py
trik.egg-info/PKG-INFO
trik.egg-info/SOURCES.txt
trik.egg-info/dependency_links.txt
trik.egg-info/requires.txt
trik.egg-info/top_level.txt
trik.egg-info/zip-safe
trik/sheng/__init__.py
trik/sheng/conv.py
trik/sheng/tensor.py
trik/ya/__init__.py
trik/ya/activation.py
trik/ya/cnnlayer.py
trik/ya/connection.py
trik/ya/loss.py
trik/ya/network.py
trik/ya/plugin.py
trik/ya/regularization.py
trik/yu/__init__.py
trik/yu/classification.py
trik/yu/darknet.py
trik/yu/data_2d.py
trik/yu/dog.jpg
trik/yu/initialization.py
trik/yu/libdarknet.so
trik/yu/mnist.py
trik/yu/pthreadGC2.dll
trik/yu/pthreadVC2.dll
trik/yu/storage.py
trik/yu/traversal.py
trik/yu/yolo_cpp_dll.dll
trik/yu/yolo_cpp_dll_no_gpu.dll
trik/yu/yolov4.cfg
trik/yu/__pycache__/__init__.cpython-35.pyc
trik/yu/__pycache__/classification.cpython-35.pyc
trik/yu/__pycache__/darknet.cpython-35.pyc
trik/yu/__pycache__/initialization.cpython-35.pyc
trik/yu/__pycache__/storage.cpython-35.pyc
trik/yu/__pycache__/traversal.cpython-35.pyc